<?xml version="1.0" encoding="utf-8"?>
<xliff xmlns="urn:oasis:names:tc:xliff:document:1.2" xmlns:xsi="http://www.w3.org/2001/XMLSchema-instance" version="1.2" xsi:schemaLocation="urn:oasis:names:tc:xliff:document:1.2 xliff-core-1.2-transitional.xsd">
  <file datatype="xml" original="TextMessageEncodingElement.xml" source-language="en-US" target-language="de-DE">
    <header>
      <tool tool-id="mdxliff" tool-name="mdxliff" tool-version="1.0-15c36f0" tool-company="Microsoft" />
      <xliffext:skl_file_name xmlns:xliffext="urn:microsoft:content:schema:xliffextensions">02cd5861-7ce2-4a82-b358-31f8435a0ac5458a211bc91e9652b3f085f5e188b67f3a3742e0.skl</xliffext:skl_file_name>
      <xliffext:version xmlns:xliffext="urn:microsoft:content:schema:xliffextensions">1.2</xliffext:version>
      <xliffext:ms.openlocfilehash xmlns:xliffext="urn:microsoft:content:schema:xliffextensions">458a211bc91e9652b3f085f5e188b67f3a3742e0</xliffext:ms.openlocfilehash>
      <xliffext:ms.sourcegitcommit xmlns:xliffext="urn:microsoft:content:schema:xliffextensions">d31dc2ede16f6f7bc64e90d9f897ff54c4e3869b</xliffext:ms.sourcegitcommit>
      <xliffext:ms.lasthandoff xmlns:xliffext="urn:microsoft:content:schema:xliffextensions">04/03/2018</xliffext:ms.lasthandoff>
      <xliffext:moniker_ids xmlns:xliffext="urn:microsoft:content:schema:xliffextensions">netframework-4.5.1,netframework-4.5.2,netframework-4.5,netframework-4.6.1,netframework-4.6.2,netframework-4.6,netframework-4.7.1,netframework-4.7</xliffext:moniker_ids>
    </header>
    <body>
      <group id="content" extype="content">
        <trans-unit id="101" translate="yes" xml:space="preserve" uid="T:System.ServiceModel.Configuration.TextMessageEncodingElement">
          <source>Represents a configuration element that specifies the character encoding and message versioning used for text-based XML messages.</source>
          <target state="translated">Stellt ein Konfigurationselement dar, das die Zeichencodierung und die für textbasierte XML-Meldungen verwendete Meldungsversionierung angibt.</target>       </trans-unit>
        <trans-unit id="102" translate="yes" xml:space="preserve" uid="T:System.ServiceModel.Configuration.TextMessageEncodingElement">
          <source>This class cannot be inherited.</source>
          <target state="translated">Diese Klasse kann nicht vererbt werden.</target>       </trans-unit>
        <trans-unit id="103" translate="yes" xml:space="preserve" extradata="MT" uid="T:System.ServiceModel.Configuration.TextMessageEncodingElement">
          <source>The text encoder creates text-based messages on the wire.</source>
          <target state="translated">Der Textencoder erstellt textbasierte Nachrichten.</target>       </trans-unit>
        <trans-unit id="104" translate="yes" xml:space="preserve" extradata="MT" uid="T:System.ServiceModel.Configuration.TextMessageEncodingElement">
          <source>Messages produced by this encoder are suitable for WS-* based interoperability.</source>
          <target state="translated">Von diesem Encoder erzeugte Meldungen sind für WS-*-basierte Interoperabilität geeignet.</target>       </trans-unit>
        <trans-unit id="105" translate="yes" xml:space="preserve" extradata="MT" uid="T:System.ServiceModel.Configuration.TextMessageEncodingElement">
          <source>Encoding is the process of transforming a set of Unicode characters into a sequence of bytes.</source>
          <target state="translated">Beim Kodieren werden Unicode-Zeichen in eine Bytefolge transformiert.</target>       </trans-unit>
        <trans-unit id="106" translate="yes" xml:space="preserve" extradata="MT" uid="T:System.ServiceModel.Configuration.TextMessageEncodingElement">
          <source>The text encoder specified by this configuration section creates text-based messages on the wire.</source>
          <target state="translated">Der von diesem Konfigurationsabschnitt angegebene Textencoder erstellt textbasierte Meldungen.</target>       </trans-unit>
        <trans-unit id="107" translate="yes" xml:space="preserve" extradata="MT" uid="T:System.ServiceModel.Configuration.TextMessageEncodingElement">
          <source>Messages produced by this encoder are suitable for WS-* based interoperability.</source>
          <target state="translated">Von diesem Encoder erzeugte Meldungen sind für WS-*-basierte Interoperabilität geeignet.</target>       </trans-unit>
        <trans-unit id="108" translate="yes" xml:space="preserve" extradata="MT" uid="T:System.ServiceModel.Configuration.TextMessageEncodingElement">
          <source>Web service or Web service client can generally understand textual XML.</source>
          <target state="translated">Der Webdienst oder Webdienstclient kann im Allgemeinen Text-XML verstehen.</target>       </trans-unit>
        <trans-unit id="109" translate="yes" xml:space="preserve" extradata="MT" uid="T:System.ServiceModel.Configuration.TextMessageEncodingElement">
          <source>However, transmitting large blocks of binary data as text is the least efficient method for encoding XML messages.</source>
          <target state="translated">Das Übertragen großer Binärdatenblöcke als Text ist allerdings die am wenigsten effiziente Methode zum Verschlüsseln von XML-Meldungen.</target>       </trans-unit>
        <trans-unit id="110" translate="yes" xml:space="preserve" extradata="MT" uid="T:System.ServiceModel.Configuration.TextMessageEncodingElement">
          <source>The <ph id="ph1">&lt;xref:System.ServiceModel.Configuration.BinaryMessageEncodingElement&gt;</ph> class represents the configuration element that specifies the character encoding and message versioning used for binary-based XML messages.</source>
          <target state="translated">Die <ph id="ph1">&lt;xref:System.ServiceModel.Configuration.BinaryMessageEncodingElement&gt;</ph>-Klasse stellt das Konfigurationselement dar, das die Zeichencodierung und die für binäre XML-Meldungen verwendete Meldungsversionierung angibt.</target>       </trans-unit>
        <trans-unit id="111" translate="yes" xml:space="preserve" extradata="MT" uid="T:System.ServiceModel.Configuration.TextMessageEncodingElement">
          <source>This is most efficient but least interoperable of the encoding options.</source>
          <target state="translated">Dies ist bezüglich der Codierungsoptionen am effizientesten, aber am wenigsten interoperabel.</target>       </trans-unit>
        <trans-unit id="112" translate="yes" xml:space="preserve" extradata="MT" uid="T:System.ServiceModel.Configuration.TextMessageEncodingElement">
          <source>The <ph id="ph1">&lt;xref:System.ServiceModel.Configuration.MtomMessageEncodingElement&gt;</ph> class represents the configuration element that specifies the character encoding and message versioning used for a message using a Message Transmission Optimization Mechanism (MTOM) encoding.</source>
          <target state="translated">Die <ph id="ph1">&lt;xref:System.ServiceModel.Configuration.MtomMessageEncodingElement&gt;</ph>-Klasse stellt das Konfigurationselement dar, das die Zeichencodierung und die für eine Meldung mit MTOM-Verschlüsselung (Message Transmission Optimization Mechanism) verwendete Meldungsversionierung angibt.</target>       </trans-unit>
        <trans-unit id="113" translate="yes" xml:space="preserve" extradata="MT" uid="T:System.ServiceModel.Configuration.TextMessageEncodingElement">
          <source>MTOM is an efficient technology for transmitting binary data in <ph id="ph1">[!INCLUDE[indigo1](~/includes/indigo1-md.md)]</ph> messages.</source>
          <target state="translated">MTOM ist eine effiziente Technologie zum Senden von Binärdaten in <ph id="ph1">[!INCLUDE[indigo1](~/includes/indigo1-md.md)]</ph>-Meldungen.</target>       </trans-unit>
        <trans-unit id="114" translate="yes" xml:space="preserve" extradata="MT" uid="T:System.ServiceModel.Configuration.TextMessageEncodingElement">
          <source>The MTOM encoder attempts to strike a balance between efficiency and interoperability.</source>
          <target state="translated">Der MTOM-Encoder versucht, einen Ausgleich zwischen Effizienz und Interoperabilität zu erreichen.</target>       </trans-unit>
        <trans-unit id="115" translate="yes" xml:space="preserve" extradata="MT" uid="T:System.ServiceModel.Configuration.TextMessageEncodingElement">
          <source>The MTOM encoding transmits most XML in textual form, but optimizes large blocks of binary data by transmitting them as-is, without conversion to text.</source>
          <target state="translated">Die MTOM-Verschlüsselung überträgt die meisten XML-Daten in Textform, optimiert aber große Binärdatenblöcke durch Übertragung ohne Textkonvertierung.</target>       </trans-unit>
        <trans-unit id="116" translate="yes" xml:space="preserve" uid="M:System.ServiceModel.Configuration.TextMessageEncodingElement.#ctor">
          <source>Initializes a new instance of the <ph id="ph1">&lt;see cref="T:System.ServiceModel.Configuration.TextMessageEncodingElement" /&gt;</ph> class.</source>
          <target state="translated">Initialisiert eine neue Instanz der <ph id="ph1">&lt;see cref="T:System.ServiceModel.Configuration.TextMessageEncodingElement" /&gt;</ph>-Klasse.</target>       </trans-unit>
        <trans-unit id="117" translate="yes" xml:space="preserve" uid="M:System.ServiceModel.Configuration.TextMessageEncodingElement.ApplyConfiguration(System.ServiceModel.Channels.BindingElement)">
          <source>A binding element.</source>
          <target state="translated">Ein Bindungselement.</target>       </trans-unit>
        <trans-unit id="118" translate="yes" xml:space="preserve" uid="M:System.ServiceModel.Configuration.TextMessageEncodingElement.ApplyConfiguration(System.ServiceModel.Channels.BindingElement)">
          <source>Applies the content of a specified binding element to this binding configuration section.</source>
          <target state="translated">Übernimmt den Inhalt eines angegebenen Bindungselements in diesen Bindungskonfigurationsabschnitt.</target>       </trans-unit>
        <trans-unit id="119" translate="yes" xml:space="preserve" uid="P:System.ServiceModel.Configuration.TextMessageEncodingElement.BindingElementType">
          <source>Gets the <ph id="ph1">&lt;see cref="T:System.Type" /&gt;</ph> of this configuration element.</source>
          <target state="translated">Ruft den <ph id="ph1">&lt;see cref="T:System.Type" /&gt;</ph> dieses Konfigurationselements ab.</target>       </trans-unit>
        <trans-unit id="120" translate="yes" xml:space="preserve" extradata="MT" uid="P:System.ServiceModel.Configuration.TextMessageEncodingElement.BindingElementType">
          <source>The <ph id="ph1">&lt;see cref="T:System.Type" /&gt;</ph> of this configuration element.</source>
          <target state="translated">Der <ph id="ph1">&lt;see cref="T:System.Type" /&gt;</ph> dieses Konfigurationselements.</target>       </trans-unit>
        <trans-unit id="121" translate="yes" xml:space="preserve" uid="M:System.ServiceModel.Configuration.TextMessageEncodingElement.CopyFrom(System.ServiceModel.Configuration.ServiceModelExtensionElement)">
          <source>The configuration section to be copied.</source>
          <target state="translated">Der zu kopierende Konfigurationsabschnitt.</target>       </trans-unit>
        <trans-unit id="122" translate="yes" xml:space="preserve" uid="M:System.ServiceModel.Configuration.TextMessageEncodingElement.CopyFrom(System.ServiceModel.Configuration.ServiceModelExtensionElement)">
          <source>Copies the content of the specified configuration section to this element.</source>
          <target state="translated">Kopiert den Inhalt des angegebenen Konfigurationselementsabschnitts in dieses Element.</target>       </trans-unit>
        <trans-unit id="123" translate="yes" xml:space="preserve" uid="P:System.ServiceModel.Configuration.TextMessageEncodingElement.MaxReadPoolSize">
          <source>Gets or sets a value that specifies the maximum number of messages that can be read simultaneously without allocating new readers.</source>
          <target state="translated">Ruft einen Wert ab oder legt einen Wert fest, der die maximale Anzahl von Meldungen angibt, die gleichzeitig gelesen werden können, ohne neue Reader zuzuordnen.</target>       </trans-unit>
        <trans-unit id="124" translate="yes" xml:space="preserve" extradata="MT" uid="P:System.ServiceModel.Configuration.TextMessageEncodingElement.MaxReadPoolSize">
          <source>The maximum number of messages that can be read simultaneously without allocating new readers.</source>
          <target state="translated">Die maximale Anzahl von Meldungen, die gleichzeitig gelesen werden können, ohne neue Reader zuzuordnen.</target>       </trans-unit>
        <trans-unit id="125" translate="yes" xml:space="preserve" extradata="MT" uid="P:System.ServiceModel.Configuration.TextMessageEncodingElement.MaxReadPoolSize">
          <source>The default is 64.</source>
          <target state="translated">Der Standard ist 64.</target>       </trans-unit>
        <trans-unit id="126" translate="yes" xml:space="preserve" extradata="MT" uid="P:System.ServiceModel.Configuration.TextMessageEncodingElement.MaxReadPoolSize">
          <source>Larger pool sizes make the system more tolerant to activity spikes at the cost of a larger working set.</source>
          <target state="translated">Durch größere Poolgrößen wird das System toleranter gegenüber Aktivitätsspitzen auf Kosten eines umfangreicheren Workingsets.</target>       </trans-unit>
        <trans-unit id="127" translate="yes" xml:space="preserve" uid="P:System.ServiceModel.Configuration.TextMessageEncodingElement.MaxWritePoolSize">
          <source>Gets or sets a value that specifies the maximum number of messages that can be sent simultaneously without allocating new writers.</source>
          <target state="translated">Ruft einen Wert ab oder legt einen Wert fest, der die maximale Anzahl von Nachrichten angibt, die gleichzeitig gesendet werden können, ohne neue Writer zuzuordnen.</target>       </trans-unit>
        <trans-unit id="128" translate="yes" xml:space="preserve" extradata="MT" uid="P:System.ServiceModel.Configuration.TextMessageEncodingElement.MaxWritePoolSize">
          <source>The maximum number of messages that can be sent simultaneously without allocating new writers.</source>
          <target state="translated">Die maximale Anzahl von Nachrichten, die gleichzeitig gesendet werden können, ohne neue Writer zuzuordnen.</target>       </trans-unit>
        <trans-unit id="129" translate="yes" xml:space="preserve" extradata="MT" uid="P:System.ServiceModel.Configuration.TextMessageEncodingElement.MaxWritePoolSize">
          <source>The default is 16.</source>
          <target state="translated">Der Standard ist 16.</target>       </trans-unit>
        <trans-unit id="130" translate="yes" xml:space="preserve" extradata="MT" uid="P:System.ServiceModel.Configuration.TextMessageEncodingElement.MaxWritePoolSize">
          <source>Larger pool sizes make the system more tolerant to activity spikes at the cost of a larger working set.</source>
          <target state="translated">Durch größere Poolgrößen wird das System toleranter gegenüber Aktivitätsspitzen auf Kosten eines umfangreicheren Workingsets.</target>       </trans-unit>
        <trans-unit id="131" translate="yes" xml:space="preserve" uid="P:System.ServiceModel.Configuration.TextMessageEncodingElement.MessageVersion">
          <source>Gets or sets the SOAP and WS-Addressing versions that are used to format the text message sent using this binding.</source>
          <target state="translated">Ruft die SOAP- und WS-Adressierungsversionen zum Formatieren der Textmeldung ab, die mithilfe dieser Bindung gesendet wird.</target>       </trans-unit>
        <trans-unit id="132" translate="yes" xml:space="preserve" extradata="MT" uid="P:System.ServiceModel.Configuration.TextMessageEncodingElement.MessageVersion">
          <source>A <ph id="ph1">&lt;see cref="T:System.ServiceModel.Channels.MessageVersion" /&gt;</ph> value that specifies the SOAP version of the messages sent using this binding.</source>
          <target state="translated">Ein <ph id="ph1">&lt;see cref="T:System.ServiceModel.Channels.MessageVersion" /&gt;</ph>-Wert, der die SOAP-Version der Meldungen angibt, die mit dieser Bindung gesendet werden.</target>       </trans-unit>
        <trans-unit id="133" translate="yes" xml:space="preserve" extradata="MT" uid="P:System.ServiceModel.Configuration.TextMessageEncodingElement.MessageVersion">
          <source>The default is <ph id="ph1">&lt;see cref="P:System.ServiceModel.Channels.MessageVersion.Soap12WSAddressing10" /&gt;</ph>.</source>
          <target state="translated">Der Standardwert ist <ph id="ph1">&lt;see cref="P:System.ServiceModel.Channels.MessageVersion.Soap12WSAddressing10" /&gt;</ph>.</target>       </trans-unit>
        <trans-unit id="134" translate="yes" xml:space="preserve" uid="P:System.ServiceModel.Configuration.TextMessageEncodingElement.ReaderQuotas">
          <source>Gets or sets constraints on the complexity of SOAP messages that can be processed by endpoints configured with this binding.</source>
          <target state="translated">Ruft Beschränkungen der Komplexität von SOAP-Meldungen ab, die von Endpunkten verarbeitet werden können, die mit dieser Bindung konfiguriert werden, oder legt die Beschränkungen fest.</target>       </trans-unit>
        <trans-unit id="135" translate="yes" xml:space="preserve" extradata="MT" uid="P:System.ServiceModel.Configuration.TextMessageEncodingElement.ReaderQuotas">
          <source>The <ph id="ph1">&lt;see cref="T:System.Xml.XmlDictionaryReaderQuotas" /&gt;</ph> that specifies the complexity constraints.</source>
          <target state="translated">Der <ph id="ph1">&lt;see cref="T:System.Xml.XmlDictionaryReaderQuotas" /&gt;</ph>, der die Komplexitätseinschränkungen angibt.</target>       </trans-unit>
        <trans-unit id="136" translate="yes" xml:space="preserve" extradata="MT" uid="P:System.ServiceModel.Configuration.TextMessageEncodingElement.ReaderQuotas">
          <source>The complexity constraints include items like a maximum element depth, or a maximum length for string content within the message.</source>
          <target state="translated">Zu den Komplexitätseinschränkungen gehören Elemente, wie z.&amp;#160;B. die maximale Elementtiefe oder die maximale Länge des Zeichenfolgeninhalts der Nachricht.</target>       </trans-unit>
        <trans-unit id="137" translate="yes" xml:space="preserve" extradata="MT" uid="P:System.ServiceModel.Configuration.TextMessageEncodingElement.ReaderQuotas">
          <source>The constraints protect against a type of denial of service (DOS) attacks that attempt to use message complexity to tie up endpoint processing resources.</source>
          <target state="translated">Die Beschränkungen schützen vor einem Typ von DOS-Angriffen (Denial Of Service), die versuchen, die Meldungskomplexität zum Binden von Endpunkt-Verarbeitungsressourcen zu verwenden.</target>       </trans-unit>
        <trans-unit id="138" translate="yes" xml:space="preserve" uid="P:System.ServiceModel.Configuration.TextMessageEncodingElement.WriteEncoding">
          <source>Gets or sets the character set encoding to be used for emitting messages on the binding.</source>
          <target state="translated">Ruft die Zeichensatzcodierung ab, die zum Ausgeben von Meldungen über die Bindung verwendet werden soll, oder legt sie fest.</target>       </trans-unit>
        <trans-unit id="139" translate="yes" xml:space="preserve" extradata="MT" uid="P:System.ServiceModel.Configuration.TextMessageEncodingElement.WriteEncoding">
          <source>A valid <ph id="ph1">&lt;see cref="T:System.Text.Encoding" /&gt;</ph> value that specifies the character set encoding to be used for emitting messages on the binding.</source>
          <target state="translated">Ein gültiger <ph id="ph1">&lt;see cref="T:System.Text.Encoding" /&gt;</ph>-Wert, der die Zeichensatzcodierung angibt, die zum Ausgeben von Nachrichten über die Bindung verwendet werden soll.</target>       </trans-unit>
        <trans-unit id="140" translate="yes" xml:space="preserve" extradata="MT" uid="P:System.ServiceModel.Configuration.TextMessageEncodingElement.WriteEncoding">
          <source>The default is <ph id="ph1">&lt;see cref="T:System.Text.UTF8Encoding" /&gt;</ph>.</source>
          <target state="translated">Der Standardwert ist <ph id="ph1">&lt;see cref="T:System.Text.UTF8Encoding" /&gt;</ph>.</target>       </trans-unit>
        <trans-unit id="141" translate="yes" xml:space="preserve" extradata="MT" uid="P:System.ServiceModel.Configuration.TextMessageEncodingElement.WriteEncoding">
          <source>When specifying a content type such as "utf-16" an XML declaration is required in the message.</source>
          <target state="translated">Wenn Sie einen Inhaltstyp angeben, wie z. B. "Utf-16" eine XML-Deklaration in der Nachricht erforderlich ist.</target>       </trans-unit>
        <trans-unit id="142" translate="yes" xml:space="preserve" extradata="MT" uid="P:System.ServiceModel.Configuration.TextMessageEncodingElement.WriteEncoding">
          <source>Alternatively you can specify either "utf-16LE" or "utf-16BE" and an XML declaration is not required.</source>
          <target state="translated">Alternativ können Sie entweder "Utf-16LE" oder "Utf-16BE" angeben und eine XML-Deklaration ist nicht erforderlich.</target>       </trans-unit>
      </group>
    </body>
  </file>
</xliff>