<?xml version="1.0" encoding="utf-8"?>
<xliff xmlns="urn:oasis:names:tc:xliff:document:1.2" xmlns:xsi="http://www.w3.org/2001/XMLSchema-instance" version="1.2" xsi:schemaLocation="urn:oasis:names:tc:xliff:document:1.2 xliff-core-1.2-transitional.xsd">
  <file datatype="xml" original="RenderOptions.xml" source-language="en-US" target-language="de-DE">
    <header>
      <tool tool-id="mdxliff" tool-name="mdxliff" tool-version="1.0-15c36f0" tool-company="Microsoft" />
      <xliffext:skl_file_name xmlns:xliffext="urn:microsoft:content:schema:xliffextensions">02cd5861-7ce2-4a82-b358-31f8435a0ac5f959d9eff690a1bec50cee0faca3f35578fff6a7.skl</xliffext:skl_file_name>
      <xliffext:version xmlns:xliffext="urn:microsoft:content:schema:xliffextensions">1.2</xliffext:version>
      <xliffext:ms.openlocfilehash xmlns:xliffext="urn:microsoft:content:schema:xliffextensions">f959d9eff690a1bec50cee0faca3f35578fff6a7</xliffext:ms.openlocfilehash>
      <xliffext:ms.sourcegitcommit xmlns:xliffext="urn:microsoft:content:schema:xliffextensions">d31dc2ede16f6f7bc64e90d9f897ff54c4e3869b</xliffext:ms.sourcegitcommit>
      <xliffext:ms.lasthandoff xmlns:xliffext="urn:microsoft:content:schema:xliffextensions">04/03/2018</xliffext:ms.lasthandoff>
      <xliffext:moniker_ids xmlns:xliffext="urn:microsoft:content:schema:xliffextensions">netframework-4.5.1,netframework-4.5.2,netframework-4.5,netframework-4.6.1,netframework-4.6.2,netframework-4.6,netframework-4.7.1,netframework-4.7</xliffext:moniker_ids>
    </header>
    <body>
      <group id="content" extype="content">
        <trans-unit id="101" translate="yes" xml:space="preserve" uid="T:System.Windows.Media.RenderOptions">
          <source>Provides options for controlling the rendering behavior of objects.</source>
          <target state="translated">Stellt Optionen zum Steuern des Renderingverhaltens von Objekten bereit.</target>       </trans-unit>
        <trans-unit id="102" translate="yes" xml:space="preserve" extradata="MT" uid="T:System.Windows.Media.RenderOptions">
          <source>You can use the attached properties of the <ph id="ph1">&lt;xref:System.Windows.Media.RenderOptions&gt;</ph> class to specify options for the rendering of text and visual elements in your WPF application.</source>
          <target state="translated">Können Sie die angefügten Eigenschaften der <ph id="ph1">&lt;xref:System.Windows.Media.RenderOptions&gt;</ph> Klasse, um Optionen für die Darstellung von Text und visuelle Elemente in der WPF-Anwendung anzugeben.</target>       </trans-unit>
        <trans-unit id="103" translate="yes" xml:space="preserve" extradata="MT" uid="T:System.Windows.Media.RenderOptions">
          <source>These options enable you to optimize rendering for speed or quality.</source>
          <target state="translated">Diese Optionen ermöglichen es Ihnen, die Darstellung für Geschwindigkeit oder Qualität optimieren.</target>       </trans-unit>
        <trans-unit id="104" translate="yes" xml:space="preserve" uid="F:System.Windows.Media.RenderOptions.BitmapScalingModeProperty">
          <source>Identifies the <ph id="ph1">&lt;see cref="P:System.Windows.Media.RenderOptions.BitmapScalingMode" /&gt;</ph> attached property.</source>
          <target state="translated">Bezeichnet die angefügte <ph id="ph1">&lt;see cref="P:System.Windows.Media.RenderOptions.BitmapScalingMode" /&gt;</ph>-Eigenschaft.</target>       </trans-unit>
        <trans-unit id="105" translate="yes" xml:space="preserve" uid="F:System.Windows.Media.RenderOptions.CacheInvalidationThresholdMaximumProperty">
          <source>Identifies the <ph id="ph1">&lt;see cref="P:System.Windows.Media.RenderOptions.CacheInvalidationThresholdMaximum" /&gt;</ph> attached property.</source>
          <target state="translated">Bezeichnet die angefügte <ph id="ph1">&lt;see cref="P:System.Windows.Media.RenderOptions.CacheInvalidationThresholdMaximum" /&gt;</ph>-Eigenschaft.</target>       </trans-unit>
        <trans-unit id="106" translate="yes" xml:space="preserve" uid="F:System.Windows.Media.RenderOptions.CacheInvalidationThresholdMinimumProperty">
          <source>Identifies the <ph id="ph1">&lt;see cref="P:System.Windows.Media.RenderOptions.CacheInvalidationThresholdMinimum" /&gt;</ph> attached property.</source>
          <target state="translated">Bezeichnet die angefügte <ph id="ph1">&lt;see cref="P:System.Windows.Media.RenderOptions.CacheInvalidationThresholdMinimum" /&gt;</ph>-Eigenschaft.</target>       </trans-unit>
        <trans-unit id="107" translate="yes" xml:space="preserve" uid="F:System.Windows.Media.RenderOptions.CachingHintProperty">
          <source>Identifies the <ph id="ph1">&lt;see cref="P:System.Windows.Media.RenderOptions.CachingHint" /&gt;</ph> attached property.</source>
          <target state="translated">Bezeichnet die angefügte <ph id="ph1">&lt;see cref="P:System.Windows.Media.RenderOptions.CachingHint" /&gt;</ph>-Eigenschaft.</target>       </trans-unit>
        <trans-unit id="108" translate="yes" xml:space="preserve" uid="F:System.Windows.Media.RenderOptions.ClearTypeHintProperty">
          <source>Identifies the <ph id="ph1">&lt;see cref="P:System.Windows.Media.RenderOptions.ClearTypeHint" /&gt;</ph> attached property.</source>
          <target state="translated">Bezeichnet die angefügte <ph id="ph1">&lt;see cref="P:System.Windows.Media.RenderOptions.ClearTypeHint" /&gt;</ph>-Eigenschaft.</target>       </trans-unit>
        <trans-unit id="109" translate="yes" xml:space="preserve" uid="F:System.Windows.Media.RenderOptions.EdgeModeProperty">
          <source>Identifies the <ph id="ph1">&lt;see cref="P:System.Windows.Media.RenderOptions.EdgeMode" /&gt;</ph> attached property.</source>
          <target state="translated">Bezeichnet die angefügte <ph id="ph1">&lt;see cref="P:System.Windows.Media.RenderOptions.EdgeMode" /&gt;</ph>-Eigenschaft.</target>       </trans-unit>
        <trans-unit id="110" translate="yes" xml:space="preserve" uid="M:System.Windows.Media.RenderOptions.GetBitmapScalingMode(System.Windows.DependencyObject)">
          <source>The dependency object from which to retrieve the value of the <ph id="ph1">&lt;see cref="P:System.Windows.Media.RenderOptions.BitmapScalingMode" /&gt;</ph> attached property.</source>
          <target state="translated">Das Abhängigkeitsobjekt, aus dem der Wert der angefügten <ph id="ph1">&lt;see cref="P:System.Windows.Media.RenderOptions.BitmapScalingMode" /&gt;</ph>-Eigenschaft abgerufen werden soll.</target>       </trans-unit>
        <trans-unit id="111" translate="yes" xml:space="preserve" uid="M:System.Windows.Media.RenderOptions.GetBitmapScalingMode(System.Windows.DependencyObject)">
          <source>Returns the value of the <ph id="ph1">&lt;see cref="P:System.Windows.Media.RenderOptions.BitmapScalingMode" /&gt;</ph> attached property for a specified dependency object.</source>
          <target state="translated">Gibt den Wert der angefügten <ph id="ph1">&lt;see cref="P:System.Windows.Media.RenderOptions.BitmapScalingMode" /&gt;</ph>-Eigenschaft für ein angegebenes Abhängigkeitsobjekt zurück.</target>       </trans-unit>
        <trans-unit id="112" translate="yes" xml:space="preserve" uid="M:System.Windows.Media.RenderOptions.GetBitmapScalingMode(System.Windows.DependencyObject)">
          <source>The current value of the <ph id="ph1">&lt;see cref="P:System.Windows.Media.RenderOptions.BitmapScalingMode" /&gt;</ph> attached property on the specified dependency object.</source>
          <target state="translated">Der aktuelle Wert der angefügten <ph id="ph1">&lt;see cref="P:System.Windows.Media.RenderOptions.BitmapScalingMode" /&gt;</ph>-Eigenschaft für das angegebene Abhängigkeitsobjekt.</target>       </trans-unit>
        <trans-unit id="113" translate="yes" xml:space="preserve" extradata="MT" uid="M:System.Windows.Media.RenderOptions.GetBitmapScalingMode(System.Windows.DependencyObject)">
          <source>The following example shows how to get the <ph id="ph1">&lt;xref:System.Windows.Media.BitmapScalingMode&gt;</ph> for an image object.</source>
          <target state="translated">Im folgende Beispiel wird gezeigt, wie zum Abrufen der <ph id="ph1">&lt;xref:System.Windows.Media.BitmapScalingMode&gt;</ph> für ein Image-Objekt.</target>       </trans-unit>
        <trans-unit id="114" translate="yes" xml:space="preserve" uid="M:System.Windows.Media.RenderOptions.GetBitmapScalingMode(System.Windows.DependencyObject)">
          <source>The specified <ph id="ph1">&lt;paramref name="target" /&gt;</ph> is <ph id="ph2">&lt;see langword="null" /&gt;</ph>.</source>
          <target state="translated">Der angegebene <ph id="ph1">&lt;paramref name="target" /&gt;</ph> ist gleich <ph id="ph2">&lt;see langword="null" /&gt;</ph>.</target>       </trans-unit>
        <trans-unit id="115" translate="yes" xml:space="preserve" uid="M:System.Windows.Media.RenderOptions.GetCacheInvalidationThresholdMaximum(System.Windows.DependencyObject)">
          <source>The dependency object from which to retrieve the value of the <ph id="ph1">&lt;see cref="P:System.Windows.Media.RenderOptions.CacheInvalidationThresholdMaximum" /&gt;</ph> attached property.</source>
          <target state="translated">Das Abhängigkeitsobjekt, aus dem der Wert der angefügten <ph id="ph1">&lt;see cref="P:System.Windows.Media.RenderOptions.CacheInvalidationThresholdMaximum" /&gt;</ph>-Eigenschaft abgerufen werden soll.</target>       </trans-unit>
        <trans-unit id="116" translate="yes" xml:space="preserve" uid="M:System.Windows.Media.RenderOptions.GetCacheInvalidationThresholdMaximum(System.Windows.DependencyObject)">
          <source>Returns the value of the <ph id="ph1">&lt;see cref="P:System.Windows.Media.RenderOptions.CacheInvalidationThresholdMaximum" /&gt;</ph> attached property for a specified dependency object.</source>
          <target state="translated">Gibt den Wert der angefügten <ph id="ph1">&lt;see cref="P:System.Windows.Media.RenderOptions.CacheInvalidationThresholdMaximum" /&gt;</ph>-Eigenschaft für ein angegebenes Abhängigkeitsobjekt zurück.</target>       </trans-unit>
        <trans-unit id="117" translate="yes" xml:space="preserve" uid="M:System.Windows.Media.RenderOptions.GetCacheInvalidationThresholdMaximum(System.Windows.DependencyObject)">
          <source>The current value of the <ph id="ph1">&lt;see cref="P:System.Windows.Media.RenderOptions.CacheInvalidationThresholdMaximum" /&gt;</ph> attached property on the specified dependency object.</source>
          <target state="translated">Der aktuelle Wert der angefügten <ph id="ph1">&lt;see cref="P:System.Windows.Media.RenderOptions.CacheInvalidationThresholdMaximum" /&gt;</ph>-Eigenschaft für das angegebene Abhängigkeitsobjekt.</target>       </trans-unit>
        <trans-unit id="118" translate="yes" xml:space="preserve" extradata="MT" uid="M:System.Windows.Media.RenderOptions.GetCacheInvalidationThresholdMaximum(System.Windows.DependencyObject)">
          <source>The following example shows how to retrieve the caching hint values for a <ph id="ph1">&lt;xref:System.Windows.Media.DrawingBrush&gt;</ph>.</source>
          <target state="translated">Im folgende Beispiel wird gezeigt, wie zum Abrufen der Zwischenspeichern Hinweis Werte für eine <ph id="ph1">&lt;xref:System.Windows.Media.DrawingBrush&gt;</ph>.</target>       </trans-unit>
        <trans-unit id="119" translate="yes" xml:space="preserve" uid="M:System.Windows.Media.RenderOptions.GetCacheInvalidationThresholdMaximum(System.Windows.DependencyObject)">
          <source>The specified <ph id="ph1">&lt;paramref name="target" /&gt;</ph> is <ph id="ph2">&lt;see langword="null" /&gt;</ph>.</source>
          <target state="translated">Der angegebene <ph id="ph1">&lt;paramref name="target" /&gt;</ph> ist gleich <ph id="ph2">&lt;see langword="null" /&gt;</ph>.</target>       </trans-unit>
        <trans-unit id="120" translate="yes" xml:space="preserve" uid="M:System.Windows.Media.RenderOptions.GetCacheInvalidationThresholdMinimum(System.Windows.DependencyObject)">
          <source>The dependency object from which to retrieve the value of the <ph id="ph1">&lt;see cref="P:System.Windows.Media.RenderOptions.CacheInvalidationThresholdMinimum" /&gt;</ph> attached property.</source>
          <target state="translated">Das Abhängigkeitsobjekt, aus dem der Wert der angefügten <ph id="ph1">&lt;see cref="P:System.Windows.Media.RenderOptions.CacheInvalidationThresholdMinimum" /&gt;</ph>-Eigenschaft abgerufen werden soll.</target>       </trans-unit>
        <trans-unit id="121" translate="yes" xml:space="preserve" uid="M:System.Windows.Media.RenderOptions.GetCacheInvalidationThresholdMinimum(System.Windows.DependencyObject)">
          <source>Returns the value of the <ph id="ph1">&lt;see cref="P:System.Windows.Media.RenderOptions.CacheInvalidationThresholdMinimum" /&gt;</ph> attached property for a specified dependency object.</source>
          <target state="translated">Gibt den Wert der angefügten <ph id="ph1">&lt;see cref="P:System.Windows.Media.RenderOptions.CacheInvalidationThresholdMinimum" /&gt;</ph>-Eigenschaft für ein angegebenes Abhängigkeitsobjekt zurück.</target>       </trans-unit>
        <trans-unit id="122" translate="yes" xml:space="preserve" uid="M:System.Windows.Media.RenderOptions.GetCacheInvalidationThresholdMinimum(System.Windows.DependencyObject)">
          <source>The current value of the <ph id="ph1">&lt;see cref="P:System.Windows.Media.RenderOptions.CacheInvalidationThresholdMinimum" /&gt;</ph> attached property on the specified dependency object.</source>
          <target state="translated">Der aktuelle Wert der angefügten <ph id="ph1">&lt;see cref="P:System.Windows.Media.RenderOptions.CacheInvalidationThresholdMinimum" /&gt;</ph>-Eigenschaft für das angegebene Abhängigkeitsobjekt.</target>       </trans-unit>
        <trans-unit id="123" translate="yes" xml:space="preserve" extradata="MT" uid="M:System.Windows.Media.RenderOptions.GetCacheInvalidationThresholdMinimum(System.Windows.DependencyObject)">
          <source>The following example shows how to retrieve the caching hint values for a <ph id="ph1">&lt;xref:System.Windows.Media.DrawingBrush&gt;</ph>.</source>
          <target state="translated">Im folgende Beispiel wird gezeigt, wie zum Abrufen der Zwischenspeichern Hinweis Werte für eine <ph id="ph1">&lt;xref:System.Windows.Media.DrawingBrush&gt;</ph>.</target>       </trans-unit>
        <trans-unit id="124" translate="yes" xml:space="preserve" uid="M:System.Windows.Media.RenderOptions.GetCacheInvalidationThresholdMinimum(System.Windows.DependencyObject)">
          <source>The specified <ph id="ph1">&lt;paramref name="target" /&gt;</ph> is <ph id="ph2">&lt;see langword="null" /&gt;</ph>.</source>
          <target state="translated">Der angegebene <ph id="ph1">&lt;paramref name="target" /&gt;</ph> ist gleich <ph id="ph2">&lt;see langword="null" /&gt;</ph>.</target>       </trans-unit>
        <trans-unit id="125" translate="yes" xml:space="preserve" uid="M:System.Windows.Media.RenderOptions.GetCachingHint(System.Windows.DependencyObject)">
          <source>The dependency object from which to retrieve the value of the <ph id="ph1">&lt;see cref="P:System.Windows.Media.RenderOptions.CachingHint" /&gt;</ph> attached property.</source>
          <target state="translated">Das Abhängigkeitsobjekt, aus dem der Wert der angefügten <ph id="ph1">&lt;see cref="P:System.Windows.Media.RenderOptions.CachingHint" /&gt;</ph>-Eigenschaft abgerufen werden soll.</target>       </trans-unit>
        <trans-unit id="126" translate="yes" xml:space="preserve" uid="M:System.Windows.Media.RenderOptions.GetCachingHint(System.Windows.DependencyObject)">
          <source>Returns the value of the <ph id="ph1">&lt;see cref="P:System.Windows.Media.RenderOptions.CachingHint" /&gt;</ph> attached property for a specified dependency object.</source>
          <target state="translated">Gibt den Wert der angefügten <ph id="ph1">&lt;see cref="P:System.Windows.Media.RenderOptions.CachingHint" /&gt;</ph>-Eigenschaft für ein angegebenes Abhängigkeitsobjekt zurück.</target>       </trans-unit>
        <trans-unit id="127" translate="yes" xml:space="preserve" uid="M:System.Windows.Media.RenderOptions.GetCachingHint(System.Windows.DependencyObject)">
          <source>The current value of the <ph id="ph1">&lt;see cref="P:System.Windows.Media.RenderOptions.CachingHint" /&gt;</ph> attached property on the specified dependency object.</source>
          <target state="translated">Der aktuelle Wert der angefügten <ph id="ph1">&lt;see cref="P:System.Windows.Media.RenderOptions.CachingHint" /&gt;</ph>-Eigenschaft für das angegebene Abhängigkeitsobjekt.</target>       </trans-unit>
        <trans-unit id="128" translate="yes" xml:space="preserve" extradata="MT" uid="M:System.Windows.Media.RenderOptions.GetCachingHint(System.Windows.DependencyObject)">
          <source>The following example shows how to retrieve the caching hint values for a <ph id="ph1">&lt;xref:System.Windows.Media.DrawingBrush&gt;</ph>.</source>
          <target state="translated">Im folgende Beispiel wird gezeigt, wie zum Abrufen der Zwischenspeichern Hinweis Werte für eine <ph id="ph1">&lt;xref:System.Windows.Media.DrawingBrush&gt;</ph>.</target>       </trans-unit>
        <trans-unit id="129" translate="yes" xml:space="preserve" uid="M:System.Windows.Media.RenderOptions.GetCachingHint(System.Windows.DependencyObject)">
          <source>The specified <ph id="ph1">&lt;paramref name="target" /&gt;</ph> is <ph id="ph2">&lt;see langword="null" /&gt;</ph>.</source>
          <target state="translated">Der angegebene <ph id="ph1">&lt;paramref name="target" /&gt;</ph> ist gleich <ph id="ph2">&lt;see langword="null" /&gt;</ph>.</target>       </trans-unit>
        <trans-unit id="130" translate="yes" xml:space="preserve" uid="M:System.Windows.Media.RenderOptions.GetClearTypeHint(System.Windows.DependencyObject)">
          <source>The <ph id="ph1">&lt;see cref="T:System.Windows.DependencyObject" /&gt;</ph> to retrieve the <ph id="ph2">&lt;see cref="P:System.Windows.Media.RenderOptions.ClearTypeHint" /&gt;</ph> attached property for.</source>
          <target state="translated">Das <ph id="ph1">&lt;see cref="T:System.Windows.DependencyObject" /&gt;</ph>, für das die angefügte <ph id="ph2">&lt;see cref="P:System.Windows.Media.RenderOptions.ClearTypeHint" /&gt;</ph>-Eigenschaft abgerufen werden soll.</target>       </trans-unit>
        <trans-unit id="131" translate="yes" xml:space="preserve" uid="M:System.Windows.Media.RenderOptions.GetClearTypeHint(System.Windows.DependencyObject)">
          <source>Gets the value of the <ph id="ph1">&lt;see cref="P:System.Windows.Media.RenderOptions.ClearTypeHint" /&gt;</ph> attached property of the specified element.</source>
          <target state="translated">Ruft den Wert der angefügten <ph id="ph1">&lt;see cref="P:System.Windows.Media.RenderOptions.ClearTypeHint" /&gt;</ph>-Eigenschaft für das angegebene Element ab.</target>       </trans-unit>
        <trans-unit id="132" translate="yes" xml:space="preserve" uid="M:System.Windows.Media.RenderOptions.GetClearTypeHint(System.Windows.DependencyObject)">
          <source>The value of the <ph id="ph1">&lt;see cref="P:System.Windows.Media.RenderOptions.ClearTypeHint" /&gt;</ph> attached property for <ph id="ph2">&lt;paramref name="target" /&gt;</ph>.</source>
          <target state="translated">Der Wert der angefügten <ph id="ph1">&lt;see cref="P:System.Windows.Media.RenderOptions.ClearTypeHint" /&gt;</ph>-Eigenschaft für <ph id="ph2">&lt;paramref name="target" /&gt;</ph>.</target>       </trans-unit>
        <trans-unit id="133" translate="yes" xml:space="preserve" uid="M:System.Windows.Media.RenderOptions.GetEdgeMode(System.Windows.DependencyObject)">
          <source>The dependency object from which to retrieve the value of the <ph id="ph1">&lt;see cref="P:System.Windows.Media.RenderOptions.EdgeMode" /&gt;</ph> attached property.</source>
          <target state="translated">Das Abhängigkeitsobjekt, aus dem der Wert der angefügten <ph id="ph1">&lt;see cref="P:System.Windows.Media.RenderOptions.EdgeMode" /&gt;</ph>-Eigenschaft abgerufen werden soll.</target>       </trans-unit>
        <trans-unit id="134" translate="yes" xml:space="preserve" uid="M:System.Windows.Media.RenderOptions.GetEdgeMode(System.Windows.DependencyObject)">
          <source>Returns the value of the <ph id="ph1">&lt;see cref="P:System.Windows.Media.RenderOptions.EdgeMode" /&gt;</ph> attached property for a specified dependency object.</source>
          <target state="translated">Gibt den Wert der angefügten <ph id="ph1">&lt;see cref="P:System.Windows.Media.RenderOptions.EdgeMode" /&gt;</ph>-Eigenschaft für ein angegebenes Abhängigkeitsobjekt zurück.</target>       </trans-unit>
        <trans-unit id="135" translate="yes" xml:space="preserve" uid="M:System.Windows.Media.RenderOptions.GetEdgeMode(System.Windows.DependencyObject)">
          <source>The current value of the <ph id="ph1">&lt;see cref="P:System.Windows.Media.RenderOptions.EdgeMode" /&gt;</ph> attached property on the specified dependency object.</source>
          <target state="translated">Der aktuelle Wert der angefügten <ph id="ph1">&lt;see cref="P:System.Windows.Media.RenderOptions.EdgeMode" /&gt;</ph>-Eigenschaft für das angegebene Abhängigkeitsobjekt.</target>       </trans-unit>
        <trans-unit id="136" translate="yes" xml:space="preserve" extradata="MT" uid="M:System.Windows.Media.RenderOptions.GetEdgeMode(System.Windows.DependencyObject)">
          <source>The default value for non-text drawing primitives, such as <ph id="ph1">&lt;xref:System.Windows.Shapes.Ellipse&gt;</ph> and <ph id="ph2">&lt;xref:System.Windows.Shapes.Polygon&gt;</ph>, is <ph id="ph3">&lt;xref:System.Windows.Media.EdgeMode.Unspecified&gt;</ph>.</source>
          <target state="translated">Der Standardwert für Zeichnungsprimitiven ohne Text, z. B. <ph id="ph1">&lt;xref:System.Windows.Shapes.Ellipse&gt;</ph> und <ph id="ph2">&lt;xref:System.Windows.Shapes.Polygon&gt;</ph>, ist <ph id="ph3">&lt;xref:System.Windows.Media.EdgeMode.Unspecified&gt;</ph>.</target>       </trans-unit>
        <trans-unit id="137" translate="yes" xml:space="preserve" uid="M:System.Windows.Media.RenderOptions.GetEdgeMode(System.Windows.DependencyObject)">
          <source>The specified <ph id="ph1">&lt;paramref name="target" /&gt;</ph> is <ph id="ph2">&lt;see langword="null" /&gt;</ph>.</source>
          <target state="translated">Der angegebene <ph id="ph1">&lt;paramref name="target" /&gt;</ph> ist gleich <ph id="ph2">&lt;see langword="null" /&gt;</ph>.</target>       </trans-unit>
        <trans-unit id="138" translate="yes" xml:space="preserve" uid="P:System.Windows.Media.RenderOptions.ProcessRenderMode">
          <source>Specifies the render mode preference for the current process.</source>
          <target state="translated">Gibt die Einstellungen des Modus zum Rendern für den aktuellen Prozess an.</target>       </trans-unit>
        <trans-unit id="139" translate="yes" xml:space="preserve" extradata="MT" uid="P:System.Windows.Media.RenderOptions.ProcessRenderMode">
          <source>The <ph id="ph1">&lt;see cref="T:System.Windows.Interop.RenderMode" /&gt;</ph> preference for the current process.</source>
          <target state="translated">Die <ph id="ph1">&lt;see cref="T:System.Windows.Interop.RenderMode" /&gt;</ph>-Einstellung für den aktuellen Prozess.</target>       </trans-unit>
        <trans-unit id="140" translate="yes" xml:space="preserve" extradata="MT" uid="P:System.Windows.Media.RenderOptions.ProcessRenderMode">
          <source>Use the <ph id="ph1">&lt;xref:System.Windows.Media.RenderOptions.ProcessRenderMode%2A&gt;</ph> property to force software rendering for the current process.</source>
          <target state="translated">Verwenden der <ph id="ph1">&lt;xref:System.Windows.Media.RenderOptions.ProcessRenderMode%2A&gt;</ph> Eigenschaft, um Elemente des Softwarerendering für den aktuellen Prozess zu erzwingen.</target>       </trans-unit>
        <trans-unit id="141" translate="yes" xml:space="preserve" extradata="MT" uid="P:System.Windows.Media.RenderOptions.ProcessRenderMode">
          <source>You can avoid many rendering issues that occur in WPF applications and that are caused by external issues if you change your preference to software rendering.</source>
          <target state="translated">Viele Probleme beim Rendern können vermieden werden, die in WPF-Anwendungen auftreten und, die durch externen Probleme verursacht werden, wenn Sie die Einstellung auf Elemente des Softwarerendering ändern.</target>       </trans-unit>
        <trans-unit id="142" translate="yes" xml:space="preserve" extradata="MT" uid="P:System.Windows.Media.RenderOptions.ProcessRenderMode">
          <source>During application startup, if your application detects rendering issues, such as slow frame rates, you can set the rendering mode to software only.</source>
          <target state="translated">Während des Anwendungsstarts Wenn Ihre Anwendung Renderingprobleme, z. B. langsame Frameraten, erkennt können Sie den Renderingmodus nur auf Software festlegen.</target>       </trans-unit>
        <trans-unit id="143" translate="yes" xml:space="preserve" extradata="MT" uid="P:System.Windows.Media.RenderOptions.ProcessRenderMode">
          <source>Also, you may want to enable the user setting while the application is running.</source>
          <target state="translated">Außerdem empfiehlt es sich zum Aktivieren der Benutzer festlegen, während die Anwendung ausgeführt wird.</target>       </trans-unit>
        <trans-unit id="144" translate="yes" xml:space="preserve" extradata="MT" uid="P:System.Windows.Media.RenderOptions.ProcessRenderMode">
          <source>The <ph id="ph1">&lt;xref:System.Windows.Interop.RenderMode.SoftwareOnly&gt;</ph> preference overrides the <ph id="ph2">&lt;xref:System.Windows.Interop.HwndTarget.RenderMode%2A&gt;</ph> setting.</source>
          <target state="translated">Die <ph id="ph1">&lt;xref:System.Windows.Interop.RenderMode.SoftwareOnly&gt;</ph> Einstellung überschreibt die <ph id="ph2">&lt;xref:System.Windows.Interop.HwndTarget.RenderMode%2A&gt;</ph> Einstellung.</target>       </trans-unit>
        <trans-unit id="145" translate="yes" xml:space="preserve" extradata="MT" uid="P:System.Windows.Media.RenderOptions.ProcessRenderMode">
          <source>The precedence order for software rendering is:</source>
          <target state="translated">Die Rangfolge für Elemente des Softwarerendering ist:</target>       </trans-unit>
        <trans-unit id="146" translate="yes" xml:space="preserve" extradata="MT" uid="P:System.Windows.Media.RenderOptions.ProcessRenderMode">
          <source>DisableHWAcceleration registry key</source>
          <target state="translated">Registrierungsschlüssel DisableHWAcceleration</target>       </trans-unit>
        <trans-unit id="147" translate="yes" xml:space="preserve" extradata="MT" uid="P:System.Windows.Media.RenderOptions.ProcessRenderMode">
          <source><ph id="ph1">&lt;xref:System.Windows.Interop.HwndTarget.RenderMode%2A&gt;</ph> (per-target)</source>
          <target state="translated"><ph id="ph1">&lt;xref:System.Windows.Interop.HwndTarget.RenderMode%2A&gt;</ph> (pro-Ziel)</target>       </trans-unit>
        <trans-unit id="148" translate="yes" xml:space="preserve" extradata="MT" uid="P:System.Windows.Media.RenderOptions.ProcessRenderMode">
          <source><bpt id="p1">**</bpt>Note<ept id="p1">**</ept> <ph id="ph1">&lt;xref:System.Windows.Media.RenderOptions.ProcessRenderMode%2A&gt;</ph> specifies a preference and does not necessarily change the actual rendering mode.</source>
          <target state="translated"><bpt id="p1">**</bpt>Hinweis<ept id="p1">**</ept> <ph id="ph1">&lt;xref:System.Windows.Media.RenderOptions.ProcessRenderMode%2A&gt;</ph> legt fest, und ändert nicht notwendigerweise den tatsächlichen Renderingmodus.</target>       </trans-unit>
        <trans-unit id="149" translate="yes" xml:space="preserve" extradata="MT" uid="P:System.Windows.Media.RenderOptions.ProcessRenderMode">
          <source>Other parts of the system may override this preference and force the system into software rendering.</source>
          <target state="translated">Andere Teile des Systems möglicherweise außer Kraft setzen diese Voreinstellung legt fest und das System in den Elemente des Softwarerendering erzwingen.</target>       </trans-unit>
        <trans-unit id="150" translate="yes" xml:space="preserve" extradata="MT" uid="P:System.Windows.Media.RenderOptions.ProcessRenderMode">
          <source>to set this property.</source>
          <target state="translated">Diese Eigenschaft festgelegt.</target>       </trans-unit>
        <trans-unit id="151" translate="yes" xml:space="preserve" extradata="MT" uid="P:System.Windows.Media.RenderOptions.ProcessRenderMode">
          <source>Associated enumeration: <ph id="ph1">&lt;see cref="F:System.Security.Permissions.UIPermissionWindow.AllWindows" /&gt;</ph></source>
          <target state="translated">Zugeordnete Enumeration: <ph id="ph1">&lt;see cref="F:System.Security.Permissions.UIPermissionWindow.AllWindows" /&gt;</ph></target>       </trans-unit>
        <trans-unit id="152" translate="yes" xml:space="preserve" uid="M:System.Windows.Media.RenderOptions.SetBitmapScalingMode(System.Windows.DependencyObject,System.Windows.Media.BitmapScalingMode)">
          <source>The <ph id="ph1">&lt;see cref="T:System.Windows.UIElement" /&gt;</ph> or <ph id="ph2">&lt;see cref="T:System.Windows.Media.DrawingGroup" /&gt;</ph> descendant on which to set the value of the <ph id="ph3">&lt;see cref="P:System.Windows.Media.RenderOptions.BitmapScalingMode" /&gt;</ph> property.</source>
          <target state="translated">Der <ph id="ph1">&lt;see cref="T:System.Windows.UIElement" /&gt;</ph>- oder der <ph id="ph2">&lt;see cref="T:System.Windows.Media.DrawingGroup" /&gt;</ph>-Nachfolger, für den der Wert der <ph id="ph3">&lt;see cref="P:System.Windows.Media.RenderOptions.BitmapScalingMode" /&gt;</ph>-Eigenschaft festgelegt werden soll.</target>       </trans-unit>
        <trans-unit id="153" translate="yes" xml:space="preserve" uid="M:System.Windows.Media.RenderOptions.SetBitmapScalingMode(System.Windows.DependencyObject,System.Windows.Media.BitmapScalingMode)">
          <source>The new value to set the property to.</source>
          <target state="translated">Der neue Wert, auf den die Eigenschaft festgelegt werden soll.</target>       </trans-unit>
        <trans-unit id="154" translate="yes" xml:space="preserve" uid="M:System.Windows.Media.RenderOptions.SetBitmapScalingMode(System.Windows.DependencyObject,System.Windows.Media.BitmapScalingMode)">
          <source>Sets the value of the <ph id="ph1">&lt;see cref="P:System.Windows.Media.RenderOptions.BitmapScalingMode" /&gt;</ph> attached property on a specified dependency object.</source>
          <target state="translated">Legt den Wert der angefügten <ph id="ph1">&lt;see cref="P:System.Windows.Media.RenderOptions.BitmapScalingMode" /&gt;</ph>-Eigenschaft für ein angegebenes Abhängigkeitsobjekt fest.</target>       </trans-unit>
        <trans-unit id="155" translate="yes" xml:space="preserve" extradata="MT" uid="M:System.Windows.Media.RenderOptions.SetBitmapScalingMode(System.Windows.DependencyObject,System.Windows.Media.BitmapScalingMode)">
          <source>Use the <ph id="ph1">&lt;xref:System.Windows.Media.RenderOptions.SetBitmapScalingMode%2A&gt;</ph> method on a <ph id="ph2">&lt;xref:System.Windows.UIElement&gt;</ph> or <ph id="ph3">&lt;xref:System.Windows.Media.DrawingGroup&gt;</ph> descendant that is animating a bitmap.</source>
          <target state="translated">Verwenden der <ph id="ph1">&lt;xref:System.Windows.Media.RenderOptions.SetBitmapScalingMode%2A&gt;</ph> Methode auf eine <ph id="ph2">&lt;xref:System.Windows.UIElement&gt;</ph> oder <ph id="ph3">&lt;xref:System.Windows.Media.DrawingGroup&gt;</ph> Nachfolger, die eine Bitmap animiert.</target>       </trans-unit>
        <trans-unit id="156" translate="yes" xml:space="preserve" extradata="MT" uid="M:System.Windows.Media.RenderOptions.SetBitmapScalingMode(System.Windows.DependencyObject,System.Windows.Media.BitmapScalingMode)">
          <source>When animating the scale of any bitmap, the default high-quality image re-sampling algorithm can sometimes consume sufficient system resources to cause frame rate degradation, effectively causing animations to stutter.</source>
          <target state="translated">Beim Animieren der Skalierung von Bitmaps kann der Standardalgorithmus für das Resampling von Bildern hoher Qualität zuweilen einen solchen Umfang an Systemressourcen beanspruchen, dass eine Verringerung der Einzelbildrate auftritt und Animationen ruckartig wiedergegeben werden.</target>       </trans-unit>
        <trans-unit id="157" translate="yes" xml:space="preserve" extradata="MT" uid="M:System.Windows.Media.RenderOptions.SetBitmapScalingMode(System.Windows.DependencyObject,System.Windows.Media.BitmapScalingMode)">
          <source>By setting the <ph id="ph1">&lt;xref:System.Windows.Media.RenderOptions.BitmapScalingMode%2A&gt;</ph> property of the <ph id="ph2">&lt;xref:System.Windows.Media.RenderOptions&gt;</ph> object to <ph id="ph3">&lt;xref:System.Windows.Media.BitmapScalingMode.LowQuality&gt;</ph>, you can create a smoother animation when scaling a bitmap.</source>
          <target state="translated">Durch Festlegen der <ph id="ph1">&lt;xref:System.Windows.Media.RenderOptions.BitmapScalingMode%2A&gt;</ph> Eigenschaft von der <ph id="ph2">&lt;xref:System.Windows.Media.RenderOptions&gt;</ph> -Objekt <ph id="ph3">&lt;xref:System.Windows.Media.BitmapScalingMode.LowQuality&gt;</ph>, Animationen erstellen, wenn eine Bitmap zu skalieren.</target>       </trans-unit>
        <trans-unit id="158" translate="yes" xml:space="preserve" extradata="MT" uid="M:System.Windows.Media.RenderOptions.SetBitmapScalingMode(System.Windows.DependencyObject,System.Windows.Media.BitmapScalingMode)">
          <source>The following example shows how to set the <ph id="ph1">&lt;xref:System.Windows.Media.BitmapScalingMode&gt;</ph> for an <ph id="ph2">&lt;xref:System.Windows.Controls.Image&gt;</ph> object.</source>
          <target state="translated">Im folgende Beispiel wird gezeigt, wie zum Festlegen der <ph id="ph1">&lt;xref:System.Windows.Media.BitmapScalingMode&gt;</ph> für ein <ph id="ph2">&lt;xref:System.Windows.Controls.Image&gt;</ph> Objekt.</target>       </trans-unit>
        <trans-unit id="159" translate="yes" xml:space="preserve" uid="M:System.Windows.Media.RenderOptions.SetBitmapScalingMode(System.Windows.DependencyObject,System.Windows.Media.BitmapScalingMode)">
          <source>The specified <ph id="ph1">&lt;paramref name="target" /&gt;</ph> is <ph id="ph2">&lt;see langword="null" /&gt;</ph>.</source>
          <target state="translated">Der angegebene <ph id="ph1">&lt;paramref name="target" /&gt;</ph> ist gleich <ph id="ph2">&lt;see langword="null" /&gt;</ph>.</target>       </trans-unit>
        <trans-unit id="160" translate="yes" xml:space="preserve" uid="M:System.Windows.Media.RenderOptions.SetCacheInvalidationThresholdMaximum(System.Windows.DependencyObject,System.Double)">
          <source>The dependency object on which to set the value of the <ph id="ph1">&lt;see cref="P:System.Windows.Media.RenderOptions.CacheInvalidationThresholdMaximum" /&gt;</ph> property</source>
          <target state="translated">Das Abhängigkeitsobjekt, für das der Wert der <ph id="ph1">&lt;see cref="P:System.Windows.Media.RenderOptions.CacheInvalidationThresholdMaximum" /&gt;</ph>-Eigenschaft festgelegt werden soll.</target>       </trans-unit>
        <trans-unit id="161" translate="yes" xml:space="preserve" uid="M:System.Windows.Media.RenderOptions.SetCacheInvalidationThresholdMaximum(System.Windows.DependencyObject,System.Double)">
          <source>The new value to set the property to.</source>
          <target state="translated">Der neue Wert, auf den die Eigenschaft festgelegt werden soll.</target>       </trans-unit>
        <trans-unit id="162" translate="yes" xml:space="preserve" uid="M:System.Windows.Media.RenderOptions.SetCacheInvalidationThresholdMaximum(System.Windows.DependencyObject,System.Double)">
          <source>Sets the value of the <ph id="ph1">&lt;see cref="P:System.Windows.Media.RenderOptions.CacheInvalidationThresholdMaximum" /&gt;</ph> attached property on a specified dependency object.</source>
          <target state="translated">Legt den Wert der angefügten <ph id="ph1">&lt;see cref="P:System.Windows.Media.RenderOptions.CacheInvalidationThresholdMaximum" /&gt;</ph>-Eigenschaft für ein angegebenes Abhängigkeitsobjekt fest.</target>       </trans-unit>
        <trans-unit id="163" translate="yes" xml:space="preserve" extradata="MT" uid="M:System.Windows.Media.RenderOptions.SetCacheInvalidationThresholdMaximum(System.Windows.DependencyObject,System.Double)">
          <source>Use this method to set the <ph id="ph1">&lt;xref:System.Windows.Media.RenderOptions.CacheInvalidationThresholdMaximum%2A&gt;</ph> attached property in code.</source>
          <target state="translated">Verwenden Sie diese Methode zum Festlegen der <ph id="ph1">&lt;xref:System.Windows.Media.RenderOptions.CacheInvalidationThresholdMaximum%2A&gt;</ph> angefügte Eigenschaft im Code.</target>       </trans-unit>
        <trans-unit id="164" translate="yes" xml:space="preserve" extradata="MT" uid="M:System.Windows.Media.RenderOptions.SetCacheInvalidationThresholdMaximum(System.Windows.DependencyObject,System.Double)">
          <source>The following example shows how to use the caching hint option for a <ph id="ph1">&lt;xref:System.Windows.Media.DrawingBrush&gt;</ph>.</source>
          <target state="translated">Das folgende Beispiel zeigt, wie Sie die Option zum Zwischenspeichern Hinweis für ein <ph id="ph1">&lt;xref:System.Windows.Media.DrawingBrush&gt;</ph>.</target>       </trans-unit>
        <trans-unit id="165" translate="yes" xml:space="preserve" uid="M:System.Windows.Media.RenderOptions.SetCacheInvalidationThresholdMaximum(System.Windows.DependencyObject,System.Double)">
          <source>The specified <ph id="ph1">&lt;paramref name="target" /&gt;</ph> is <ph id="ph2">&lt;see langword="null" /&gt;</ph>.</source>
          <target state="translated">Der angegebene <ph id="ph1">&lt;paramref name="target" /&gt;</ph> ist gleich <ph id="ph2">&lt;see langword="null" /&gt;</ph>.</target>       </trans-unit>
        <trans-unit id="166" translate="yes" xml:space="preserve" uid="M:System.Windows.Media.RenderOptions.SetCacheInvalidationThresholdMinimum(System.Windows.DependencyObject,System.Double)">
          <source>The dependency object on which to set the value of the <ph id="ph1">&lt;see cref="P:System.Windows.Media.RenderOptions.CacheInvalidationThresholdMinimum" /&gt;</ph> property</source>
          <target state="translated">Das Abhängigkeitsobjekt, für das der Wert der <ph id="ph1">&lt;see cref="P:System.Windows.Media.RenderOptions.CacheInvalidationThresholdMinimum" /&gt;</ph>-Eigenschaft festgelegt werden soll.</target>       </trans-unit>
        <trans-unit id="167" translate="yes" xml:space="preserve" uid="M:System.Windows.Media.RenderOptions.SetCacheInvalidationThresholdMinimum(System.Windows.DependencyObject,System.Double)">
          <source>The new value to set the property to.</source>
          <target state="translated">Der neue Wert, auf den die Eigenschaft festgelegt werden soll.</target>       </trans-unit>
        <trans-unit id="168" translate="yes" xml:space="preserve" uid="M:System.Windows.Media.RenderOptions.SetCacheInvalidationThresholdMinimum(System.Windows.DependencyObject,System.Double)">
          <source>Sets the value of the <ph id="ph1">&lt;see cref="P:System.Windows.Media.RenderOptions.CacheInvalidationThresholdMinimum" /&gt;</ph> attached property on a specified dependency object.</source>
          <target state="translated">Legt den Wert der angefügten <ph id="ph1">&lt;see cref="P:System.Windows.Media.RenderOptions.CacheInvalidationThresholdMinimum" /&gt;</ph>-Eigenschaft für ein angegebenes Abhängigkeitsobjekt fest.</target>       </trans-unit>
        <trans-unit id="169" translate="yes" xml:space="preserve" extradata="MT" uid="M:System.Windows.Media.RenderOptions.SetCacheInvalidationThresholdMinimum(System.Windows.DependencyObject,System.Double)">
          <source>Use this method to set the <ph id="ph1">&lt;xref:System.Windows.Media.RenderOptions.CacheInvalidationThresholdMinimum%2A&gt;</ph> attached property in code.</source>
          <target state="translated">Verwenden Sie diese Methode zum Festlegen der <ph id="ph1">&lt;xref:System.Windows.Media.RenderOptions.CacheInvalidationThresholdMinimum%2A&gt;</ph> angefügte Eigenschaft im Code.</target>       </trans-unit>
        <trans-unit id="170" translate="yes" xml:space="preserve" extradata="MT" uid="M:System.Windows.Media.RenderOptions.SetCacheInvalidationThresholdMinimum(System.Windows.DependencyObject,System.Double)">
          <source>The following example shows how to use the caching hint option for a <ph id="ph1">&lt;xref:System.Windows.Media.DrawingBrush&gt;</ph>.</source>
          <target state="translated">Das folgende Beispiel zeigt, wie Sie die Option zum Zwischenspeichern Hinweis für ein <ph id="ph1">&lt;xref:System.Windows.Media.DrawingBrush&gt;</ph>.</target>       </trans-unit>
        <trans-unit id="171" translate="yes" xml:space="preserve" uid="M:System.Windows.Media.RenderOptions.SetCacheInvalidationThresholdMinimum(System.Windows.DependencyObject,System.Double)">
          <source>The specified <ph id="ph1">&lt;paramref name="target" /&gt;</ph> is <ph id="ph2">&lt;see langword="null" /&gt;</ph>.</source>
          <target state="translated">Der angegebene <ph id="ph1">&lt;paramref name="target" /&gt;</ph> ist gleich <ph id="ph2">&lt;see langword="null" /&gt;</ph>.</target>       </trans-unit>
        <trans-unit id="172" translate="yes" xml:space="preserve" uid="M:System.Windows.Media.RenderOptions.SetCachingHint(System.Windows.DependencyObject,System.Windows.Media.CachingHint)">
          <source>The dependency object on which to set the value of the <ph id="ph1">&lt;see cref="P:System.Windows.Media.RenderOptions.CachingHint" /&gt;</ph> property.</source>
          <target state="translated">Das Abhängigkeitsobjekt, für das der Wert der <ph id="ph1">&lt;see cref="P:System.Windows.Media.RenderOptions.CachingHint" /&gt;</ph>-Eigenschaft festgelegt werden soll.</target>       </trans-unit>
        <trans-unit id="173" translate="yes" xml:space="preserve" uid="M:System.Windows.Media.RenderOptions.SetCachingHint(System.Windows.DependencyObject,System.Windows.Media.CachingHint)">
          <source>The new value to set the property to.</source>
          <target state="translated">Der neue Wert, auf den die Eigenschaft festgelegt werden soll.</target>       </trans-unit>
        <trans-unit id="174" translate="yes" xml:space="preserve" uid="M:System.Windows.Media.RenderOptions.SetCachingHint(System.Windows.DependencyObject,System.Windows.Media.CachingHint)">
          <source>Sets the value of the <ph id="ph1">&lt;see cref="P:System.Windows.Media.RenderOptions.CachingHint" /&gt;</ph> attached property on a specified dependency object.</source>
          <target state="translated">Legt den Wert der angefügten <ph id="ph1">&lt;see cref="P:System.Windows.Media.RenderOptions.CachingHint" /&gt;</ph>-Eigenschaft für ein angegebenes Abhängigkeitsobjekt fest.</target>       </trans-unit>
        <trans-unit id="175" translate="yes" xml:space="preserve" extradata="MT" uid="M:System.Windows.Media.RenderOptions.SetCachingHint(System.Windows.DependencyObject,System.Windows.Media.CachingHint)">
          <source>By default, <ph id="ph1">[!INCLUDE[TLA2#tla_winclient](~/includes/tla2sharptla-winclient-md.md)]</ph> does not cache the rendered contents of <ph id="ph2">&lt;xref:System.Windows.Media.DrawingBrush&gt;</ph> and <ph id="ph3">&lt;xref:System.Windows.Media.VisualBrush&gt;</ph> objects.</source>
          <target state="translated">Standardmäßig <ph id="ph1">[!INCLUDE[TLA2#tla_winclient](~/includes/tla2sharptla-winclient-md.md)]</ph> zwischenspeichert, den gerenderten Inhalt <ph id="ph2">&lt;xref:System.Windows.Media.DrawingBrush&gt;</ph> und <ph id="ph3">&lt;xref:System.Windows.Media.VisualBrush&gt;</ph> Objekte.</target>       </trans-unit>
        <trans-unit id="176" translate="yes" xml:space="preserve" extradata="MT" uid="M:System.Windows.Media.RenderOptions.SetCachingHint(System.Windows.DependencyObject,System.Windows.Media.CachingHint)">
          <source>In static scenarios, where neither the contents nor the use of the brush in the scene is changing, not caching provides a benefit because it conserves video memory.</source>
          <target state="translated">In statischen Szenarien, in denen der Inhalt weder die Verwendung des Pinsels in der Szene geändert wird, bietet nicht Zwischenspeichern der Vorteil, da Videospeicher gespart wird.</target>       </trans-unit>
        <trans-unit id="177" translate="yes" xml:space="preserve" extradata="MT" uid="M:System.Windows.Media.RenderOptions.SetCachingHint(System.Windows.DependencyObject,System.Windows.Media.CachingHint)">
          <source>When a brush with static content is used in a non-static way, the default behavior of <ph id="ph1">[!INCLUDE[TLA2#tla_winclient](~/includes/tla2sharptla-winclient-md.md)]</ph> is to re-render all the content of the brush every frame, even though the content is unchanging.</source>
          <target state="translated">Wenn ein Pinsel mit statischem Inhalt verwendet wird, auf eine nicht statische Weise das Standardverhalten des <ph id="ph1">[!INCLUDE[TLA2#tla_winclient](~/includes/tla2sharptla-winclient-md.md)]</ph> entspricht der gesamte Inhalt des Pinsels erneut zu rendern jeden Frame, selbst wenn der Inhalt unverändert bleibt.</target>       </trans-unit>
        <trans-unit id="178" translate="yes" xml:space="preserve" extradata="MT" uid="M:System.Windows.Media.RenderOptions.SetCachingHint(System.Windows.DependencyObject,System.Windows.Media.CachingHint)">
          <source>For example, this will happen when a static <ph id="ph1">&lt;xref:System.Windows.Media.DrawingBrush&gt;</ph> or <ph id="ph2">&lt;xref:System.Windows.Media.VisualBrush&gt;</ph> is mapped to the surface of a rotating 3D object.</source>
          <target state="translated">Dies wird z. B. vorkommen, wenn ein statischer <ph id="ph1">&lt;xref:System.Windows.Media.DrawingBrush&gt;</ph> oder <ph id="ph2">&lt;xref:System.Windows.Media.VisualBrush&gt;</ph> auf die Oberfläche eines Objekts für das Drehen von 3D zugeordnet ist.</target>       </trans-unit>
        <trans-unit id="179" translate="yes" xml:space="preserve" extradata="MT" uid="M:System.Windows.Media.RenderOptions.SetCachingHint(System.Windows.DependencyObject,System.Windows.Media.CachingHint)">
          <source>Re-rendering the static content can have a negative impact on performance.</source>
          <target state="translated">Den statischen Inhalt erneut rendern kann sich negativ auf die Leistung auswirken.</target>       </trans-unit>
        <trans-unit id="180" translate="yes" xml:space="preserve" extradata="MT" uid="M:System.Windows.Media.RenderOptions.SetCachingHint(System.Windows.DependencyObject,System.Windows.Media.CachingHint)">
          <source>By setting the <ph id="ph1">&lt;xref:System.Windows.Media.RenderOptions.CachingHint%2A&gt;</ph> attached property of the brush to <ph id="ph2">&lt;xref:System.Windows.Media.CachingHint.Cache&gt;</ph>, you can increase performance by using cached versions of the tiled brush objects.</source>
          <target state="translated">Durch Festlegen der <ph id="ph1">&lt;xref:System.Windows.Media.RenderOptions.CachingHint%2A&gt;</ph> -Eigenschaft des Pinsels auf <ph id="ph2">&lt;xref:System.Windows.Media.CachingHint.Cache&gt;</ph>, Sie können die Leistung mithilfe von zwischengespeicherten Versionen der Kacheleffekt Objekte erhöhen.</target>       </trans-unit>
        <trans-unit id="181" translate="yes" xml:space="preserve" extradata="MT" uid="M:System.Windows.Media.RenderOptions.SetCachingHint(System.Windows.DependencyObject,System.Windows.Media.CachingHint)">
          <source>The <ph id="ph1">&lt;xref:System.Windows.Media.RenderOptions.CacheInvalidationThresholdMinimum%2A&gt;</ph> and <ph id="ph2">&lt;xref:System.Windows.Media.RenderOptions.CacheInvalidationThresholdMaximum%2A&gt;</ph> property values are relative-size values that determine when the <ph id="ph3">&lt;xref:System.Windows.Media.TileBrush&gt;</ph> object should be regenerated because of changes in scale.</source>
          <target state="translated">Die <ph id="ph1">&lt;xref:System.Windows.Media.RenderOptions.CacheInvalidationThresholdMinimum%2A&gt;</ph> und <ph id="ph2">&lt;xref:System.Windows.Media.RenderOptions.CacheInvalidationThresholdMaximum%2A&gt;</ph> Eigenschaftswerte sind Werte von relativer Größe, die bestimmen, wann die <ph id="ph3">&lt;xref:System.Windows.Media.TileBrush&gt;</ph> Objekt aufgrund von Änderungen an der Skalierung neu generiert werden sollte.</target>       </trans-unit>
        <trans-unit id="182" translate="yes" xml:space="preserve" extradata="MT" uid="M:System.Windows.Media.RenderOptions.SetCachingHint(System.Windows.DependencyObject,System.Windows.Media.CachingHint)">
          <source>For example, when the <ph id="ph1">&lt;xref:System.Windows.Media.RenderOptions.CacheInvalidationThresholdMaximum%2A&gt;</ph> property is set to 2.0, the cache for the <ph id="ph2">&lt;xref:System.Windows.Media.TileBrush&gt;</ph> needs to be regenerated only when its size exceeds two times the size of the current cache.</source>
          <target state="translated">Beispielsweise, wenn die <ph id="ph1">&lt;xref:System.Windows.Media.RenderOptions.CacheInvalidationThresholdMaximum%2A&gt;</ph> Eigenschaftensatz zu 2.0, den Cache für die <ph id="ph2">&lt;xref:System.Windows.Media.TileBrush&gt;</ph> muss erneut generiert werden, nur, wenn seine Größe zweimal die Größe des aktuellen Caches überschreitet.</target>       </trans-unit>
        <trans-unit id="183" translate="yes" xml:space="preserve" extradata="MT" uid="M:System.Windows.Media.RenderOptions.SetCachingHint(System.Windows.DependencyObject,System.Windows.Media.CachingHint)">
          <source>Use this method to set the <ph id="ph1">&lt;xref:System.Windows.Media.RenderOptions.CachingHint%2A&gt;</ph> attached property in code.</source>
          <target state="translated">Verwenden Sie diese Methode zum Festlegen der <ph id="ph1">&lt;xref:System.Windows.Media.RenderOptions.CachingHint%2A&gt;</ph> angefügte Eigenschaft im Code.</target>       </trans-unit>
        <trans-unit id="184" translate="yes" xml:space="preserve" extradata="MT" uid="M:System.Windows.Media.RenderOptions.SetCachingHint(System.Windows.DependencyObject,System.Windows.Media.CachingHint)">
          <source>The following example shows how to use the caching hint option for a <ph id="ph1">&lt;xref:System.Windows.Media.DrawingBrush&gt;</ph>.</source>
          <target state="translated">Das folgende Beispiel zeigt, wie Sie die Option zum Zwischenspeichern Hinweis für ein <ph id="ph1">&lt;xref:System.Windows.Media.DrawingBrush&gt;</ph>.</target>       </trans-unit>
        <trans-unit id="185" translate="yes" xml:space="preserve" uid="M:System.Windows.Media.RenderOptions.SetCachingHint(System.Windows.DependencyObject,System.Windows.Media.CachingHint)">
          <source>The specified <ph id="ph1">&lt;paramref name="target" /&gt;</ph> is <ph id="ph2">&lt;see langword="null" /&gt;</ph>.</source>
          <target state="translated">Der angegebene <ph id="ph1">&lt;paramref name="target" /&gt;</ph> ist gleich <ph id="ph2">&lt;see langword="null" /&gt;</ph>.</target>       </trans-unit>
        <trans-unit id="186" translate="yes" xml:space="preserve" uid="M:System.Windows.Media.RenderOptions.SetClearTypeHint(System.Windows.DependencyObject,System.Windows.Media.ClearTypeHint)">
          <source>The <ph id="ph1">&lt;see cref="T:System.Windows.DependencyObject" /&gt;</ph> to set the <ph id="ph2">&lt;see cref="P:System.Windows.Media.RenderOptions.ClearTypeHint" /&gt;</ph> attached property on.</source>
          <target state="translated">Das <ph id="ph1">&lt;see cref="T:System.Windows.DependencyObject" /&gt;</ph>, für das die angefügte <ph id="ph2">&lt;see cref="P:System.Windows.Media.RenderOptions.ClearTypeHint" /&gt;</ph>-Eigenschaft festgelegt werden soll.</target>       </trans-unit>
        <trans-unit id="187" translate="yes" xml:space="preserve" uid="M:System.Windows.Media.RenderOptions.SetClearTypeHint(System.Windows.DependencyObject,System.Windows.Media.ClearTypeHint)">
          <source>The new <ph id="ph1">&lt;see cref="P:System.Windows.Media.RenderOptions.ClearTypeHint" /&gt;</ph> value.</source>
          <target state="translated">Der neue <ph id="ph1">&lt;see cref="P:System.Windows.Media.RenderOptions.ClearTypeHint" /&gt;</ph>-Wert.</target>       </trans-unit>
        <trans-unit id="188" translate="yes" xml:space="preserve" uid="M:System.Windows.Media.RenderOptions.SetClearTypeHint(System.Windows.DependencyObject,System.Windows.Media.ClearTypeHint)">
          <source>Sets the value of the <ph id="ph1">&lt;see cref="P:System.Windows.Media.RenderOptions.ClearTypeHint" /&gt;</ph> attached property of the specified element.</source>
          <target state="translated">Legt den Wert der angefügten <ph id="ph1">&lt;see cref="P:System.Windows.Media.RenderOptions.ClearTypeHint" /&gt;</ph>-Eigenschaft für das angegebene Element fest.</target>       </trans-unit>
        <trans-unit id="189" translate="yes" xml:space="preserve" uid="M:System.Windows.Media.RenderOptions.SetClearTypeHint(System.Windows.DependencyObject,System.Windows.Media.ClearTypeHint)">
          <source>The specified <ph id="ph1">&lt;paramref name="target" /&gt;</ph> is <ph id="ph2">&lt;see langword="null" /&gt;</ph>.</source>
          <target state="translated">Der angegebene <ph id="ph1">&lt;paramref name="target" /&gt;</ph> ist gleich <ph id="ph2">&lt;see langword="null" /&gt;</ph>.</target>       </trans-unit>
        <trans-unit id="190" translate="yes" xml:space="preserve" uid="M:System.Windows.Media.RenderOptions.SetEdgeMode(System.Windows.DependencyObject,System.Windows.Media.EdgeMode)">
          <source>The dependency object on which to set the value of the <ph id="ph1">&lt;see cref="P:System.Windows.Media.RenderOptions.EdgeMode" /&gt;</ph> property</source>
          <target state="translated">Das Abhängigkeitsobjekt, für das der Wert der <ph id="ph1">&lt;see cref="P:System.Windows.Media.RenderOptions.EdgeMode" /&gt;</ph>-Eigenschaft festgelegt werden soll.</target>       </trans-unit>
        <trans-unit id="191" translate="yes" xml:space="preserve" uid="M:System.Windows.Media.RenderOptions.SetEdgeMode(System.Windows.DependencyObject,System.Windows.Media.EdgeMode)">
          <source>The new value to set the property to.</source>
          <target state="translated">Der neue Wert, auf den die Eigenschaft festgelegt werden soll.</target>       </trans-unit>
        <trans-unit id="192" translate="yes" xml:space="preserve" uid="M:System.Windows.Media.RenderOptions.SetEdgeMode(System.Windows.DependencyObject,System.Windows.Media.EdgeMode)">
          <source>Sets the value of the <ph id="ph1">&lt;see cref="P:System.Windows.Media.RenderOptions.EdgeMode" /&gt;</ph> attached property on a specified dependency object.</source>
          <target state="translated">Legt den Wert der angefügten <ph id="ph1">&lt;see cref="P:System.Windows.Media.RenderOptions.EdgeMode" /&gt;</ph>-Eigenschaft für ein angegebenes Abhängigkeitsobjekt fest.</target>       </trans-unit>
        <trans-unit id="193" translate="yes" xml:space="preserve" extradata="MT" uid="M:System.Windows.Media.RenderOptions.SetEdgeMode(System.Windows.DependencyObject,System.Windows.Media.EdgeMode)">
          <source>Text objects are always displayed with anti-aliasing, and are unaffected by setting the edge mode value.</source>
          <target state="translated">Textobjekte werden immer mit Antialiasing angezeigt und durch Festlegen des Werts des Edge-Modus nicht betroffen sind.</target>       </trans-unit>
        <trans-unit id="194" translate="yes" xml:space="preserve" extradata="MT" uid="M:System.Windows.Media.RenderOptions.SetEdgeMode(System.Windows.DependencyObject,System.Windows.Media.EdgeMode)">
          <source>When you set the edge mode value of a visual object, all the descendant drawing primitives of the visual object are set to the same edge mode value.</source>
          <target state="translated">Wenn Sie den Wert des Edge-Modus eines visuellen Objekts festlegen, werden alle untergeordneten Zeichnungsprimitiven des visuellen Objekts auf den gleichen Wert des Edge-Modus festgelegt.</target>       </trans-unit>
        <trans-unit id="195" translate="yes" xml:space="preserve" extradata="MT" uid="M:System.Windows.Media.RenderOptions.SetEdgeMode(System.Windows.DependencyObject,System.Windows.Media.EdgeMode)">
          <source>The following example shows how to use the <ph id="ph1">&lt;xref:System.Windows.Media.RenderOptions.SetEdgeMode%2A&gt;</ph> method to set the edge mode for a visual object to <ph id="ph2">&lt;xref:System.Windows.Media.EdgeMode.Aliased&gt;</ph>.</source>
          <target state="translated">Das folgende Beispiel zeigt, wie Sie die <ph id="ph1">&lt;xref:System.Windows.Media.RenderOptions.SetEdgeMode%2A&gt;</ph> -Methode zum Festlegen der Edge-Modus für ein visuelles Objekt zu <ph id="ph2">&lt;xref:System.Windows.Media.EdgeMode.Aliased&gt;</ph>.</target>       </trans-unit>
        <trans-unit id="196" translate="yes" xml:space="preserve" uid="M:System.Windows.Media.RenderOptions.SetEdgeMode(System.Windows.DependencyObject,System.Windows.Media.EdgeMode)">
          <source>The specified <ph id="ph1">&lt;paramref name="target" /&gt;</ph> is <ph id="ph2">&lt;see langword="null" /&gt;</ph>.</source>
          <target state="translated">Der angegebene <ph id="ph1">&lt;paramref name="target" /&gt;</ph> ist gleich <ph id="ph2">&lt;see langword="null" /&gt;</ph>.</target>       </trans-unit>
      </group>
    </body>
  </file>
</xliff>